best_profanity/__init__.py
best_profanity/best_profanity.py
best_profanity/data/english-model.joblib
best_profanity/data/english-vectorizer.joblib
best_profanity/data/tagalog-model.joblib
best_profanity/data/tagalog-vectorizer.joblib
best_profanity-1.1.5.dist-info/LICENSE
best_profanity-1.1.5.dist-info/METADATA
best_profanity-1.1.5.dist-info/WHEEL
best_profanity-1.1.5.dist-info/top_level.txt
best_profanity-1.1.5.dist-info/RECORD
