Metadata-Version: 2.1
Name: best-profanity
Version: 1.1.5
Summary: An efficient, and accurate machine learning model for detecting profane or vulgar terminology in both English and Filipino languages, including current Gen Z slang and expressions.
Author: Victor Zhou, 2021 Menelaos Kotoglou, Dimitrios Mistriotis, and Joey Nicole Mindo
Author-email: joeynicole99@gmail.com
Classifier: Development Status :: 5 - Production/Stable
Classifier: Natural Language :: English
Classifier: Programming Language :: Python :: 3
Classifier: License :: OSI Approved :: MIT License
Classifier: Operating System :: OS Independent
Requires-Python: >=3.8
License-File: LICENSE
Requires-Dist: scikit-learn ==1.3.2
Requires-Dist: joblib >=1.3.2
